MANIFEST.in
README.md
VERSION
darbe.py
setup.cfg
setup.py
Darbe.egg-info/PKG-INFO
Darbe.egg-info/SOURCES.txt
Darbe.egg-info/dependency_links.txt
Darbe.egg-info/entry_points.txt
Darbe.egg-info/requires.txt
Darbe.egg-info/top_level.txt