Metadata-Version: 1.0
Name: Darbe
Version: 1.4.1
Summary: RDS MySQL replication setup tool
Home-page: https://github.com/cenk/darbe
Author: Cenk Altı
Author-email: cenkalti@gmail.com
License: UNKNOWN
Keywords: mysql rds migration database replication slave
Platform: UNKNOWN
